hrms_utils/__init__.py
hrms_utils/formats/__init__.py
hrms_utils/formats/epa_xlsx.py
hrms_utils/formats/mgf.py
hrms_utils/formats/msdial.py
hrms_utils/formats/nist_mspec.py
hrms_utils/formats/pubchem.py
hrms_utils/formula_annotation/__init__.py
hrms_utils/formula_annotation/element_table.py
hrms_utils/formula_annotation/isotopic_pattern.py
hrms_utils/formula_annotation/mass_decomposition.py
hrms_utils/formula_annotation/ms_buddy.py
hrms_utils/formula_annotation/sirius.py
hrms_utils/formula_annotation/utils.py
hrms_utils/formula_annotation/mass_decomposition_impl/__init__.py
hrms_utils/formula_annotation/mass_decomposition_impl/benchmark.py
hrms_utils/formula_annotation/mass_decomposition_impl/mass_decomposer_common.cpp
hrms_utils/formula_annotation/mass_decomposition_impl/mass_decomposer_common.hpp
hrms_utils/formula_annotation/mass_decomposition_impl/mass_decomposer_cpp.cp312-win_amd64.pyd
hrms_utils/formula_annotation/mass_decomposition_impl/mass_decomposer_cpp.cpp
hrms_utils/formula_annotation/mass_decomposition_impl/mass_decomposer_cpp.pyx
hrms_utils/formula_annotation/mass_decomposition_impl/mass_decomposer_money_changing.cpp
hrms_utils/formula_annotation/mass_decomposition_impl/mass_decomposer_parallel.cpp
hrms_utils/formula_annotation/mass_decomposition_impl/setup_bk.py
hrms_utils/rdkit/__init__.py
hrms_utils/rdkit/fingerprint.py
hrms_utils/rdkit/fragmentation.py
hrms_utils/rdkit/mol.py
hrms_utils/spectral_information/__init__.py
hrms_utils/spectral_information/spectral_info_score.py
hrms_utils/spectral_information/tree_spectral_info_score.py
hrms_utils-0.6.2.dist-info/METADATA
hrms_utils-0.6.2.dist-info/WHEEL
hrms_utils-0.6.2.dist-info/top_level.txt
hrms_utils-0.6.2.dist-info/RECORD
