Metadata-Version: 2.4
Name: hrms_utils
Version: 0.6.2
Requires-Python: >=3.12
Requires-Dist: polars<2,>=1.33.0
Requires-Dist: rdkit>=2024.0.0
Requires-Dist: numpy>=1.20.0
Requires-Dist: numba>=0.61.0
Requires-Dist: ms_entropy
Requires-Dist: requests
Requires-Dist: aiohttp
Requires-Dist: scipy
Requires-Dist: pyarrow>=12.0.0
Requires-Dist: pandas
Requires-Dist: openpyxl
Requires-Dist: python-calamine
Requires-Dist: xlsx2csv
Requires-Dist: xlsxwriter
Requires-Dist: connectorx
Requires-Dist: sqlalchemy
